controlib/__init__.py
controlib/_version.py
controlib/controllers/base.py
controlib/state_estimators/base.py
controlib-0.1.0.dist-info/LICENSE
controlib-0.1.0.dist-info/METADATA
controlib-0.1.0.dist-info/WHEEL
controlib-0.1.0.dist-info/top_level.txt
controlib-0.1.0.dist-info/RECORD
