Metadata-Version: 2.1
Name: controlib
Version: 0.1.0
Summary: A Python package for advanced control systems design and deployment.
Author-email: Miguel Santos Loureiro <miguel.santos.loureiro@gmail.com>
Maintainer-email: Miguel Santos Loureiro <miguel.santos.loureiro@gmail.com>
License:                     GNU GENERAL PUBLIC LICENSE
Project-URL: repository, https://github.com/MiguelLoureiro98/controlib
Keywords: Control Systems,Machine Learning,Optimisation,Deployment
Classifier: Programming Language :: Python :: 3
Classifier: License :: OSI Approved :: GNU General Public License v3 (GPLv3)
Classifier: Natural Language :: English
Classifier: Operating System :: OS Independent
Classifier: Topic :: Software Development :: Libraries :: Python Modules
Classifier: Topic :: Scientific/Engineering
Classifier: Intended Audience :: Science/Research
Classifier: Intended Audience :: Developers
Classifier: Intended Audience :: Education
Requires-Python: >=3.10
License-File: LICENSE
Requires-Dist: numpy>=2.1.3
Provides-Extra: dev
Requires-Dist: pytest>=8.3.3; extra == "dev"
Requires-Dist: mkdocs>=1.6.1; extra == "dev"
Requires-Dist: mkdocs-material>=9.5.45; extra == "dev"
Requires-Dist: mkdocs-material-extensions>=1.3.1; extra == "dev"
Requires-Dist: mkdocstrings-python>=1.12.2; extra == "dev"
Requires-Dist: build>=1.2.2; extra == "dev"
